asimov/__init__.py
asimov/_version.py
asimov/py.typed
asimov_py-26.0.0.dev0.dist-info/METADATA
asimov_py-26.0.0.dev0.dist-info/WHEEL
asimov_py-26.0.0.dev0.dist-info/licenses/UNLICENSE
asimov_py-26.0.0.dev0.dist-info/RECORD
