Metadata-Version: 2.4
Name: asimov.py
Version: 26.0.0.dev0
Summary: ASIMOV Software Development Kit (SDK) for Python
Project-URL: Homepage, https://asimov.sh
Project-URL: Repository, https://github.com/asimov-platform/asimov.py
Project-URL: Changelog, https://github.com/asimov-platform/asimov.py/blob/master/CHANGES.md
Project-URL: Releases, https://github.com/asimov-platform/asimov.py/releases
Project-URL: Issues, https://github.com/asimov-platform/asimov.py/issues
Project-URL: Documentation, https://github.com/asimov-platform/asimov.py/blob/master/README.md
Author-email: ASIMOV Systems <support@asimov.systems>
License-Expression: Unlicense
License-File: UNLICENSE
Classifier: Development Status :: 2 - Pre-Alpha
Classifier: Environment :: Console
Classifier: Intended Audience :: Developers
Classifier: Intended Audience :: Information Technology
Classifier: License :: Public Domain
Classifier: Natural Language :: English
Classifier: Operating System :: OS Independent
Classifier: Programming Language :: Python :: 3 :: Only
Classifier: Topic :: Software Development :: Libraries
Requires-Python: >=3.9
Requires-Dist: pydantic>=2
